{"cameraMode":{"drawMode":0,"name":"Shaded","section":"Shading Mode"},"sceneLighting":false,"audioPlay":false,"sceneViewState":{"m_AlwaysRefresh":false,"showFog":true,"showSkybox":false,"showFlares":true,"showImageEffects":true,"showParticleSystems":true,"showVisualEffectGraphs":true,"m_FxEnabled":true},"in2DMode":false,"pivot":{"x":3.820000171661377,"y":1.2807369232177735,"z":0.1407405138015747},"rotation":{"x":0.029993314296007158,"y":0.9605035185813904,"z":-0.25191810727119448,"w":0.11435453593730927},"size":2.5429115295410158,"orthographic":false}